juntagrico_billing/__init__.py
juntagrico_billing/apps.py
juntagrico_billing/config.py
juntagrico_billing/mailer.py
juntagrico_billing/urls.py
juntagrico_billing/views.py
juntagrico_billing/views_payment.py
juntagrico_billing/admin/__init__.py
juntagrico_billing/admin/bill.py
juntagrico_billing/admin/billitem_inline.py
juntagrico_billing/admin/businessyear.py
juntagrico_billing/admin/payment.py
juntagrico_billing/admin/payment_inline.py
juntagrico_billing/lifecycle/__init__.py
juntagrico_billing/lifecycle/billitem.py
juntagrico_billing/lifecycle/payment.py
juntagrico_billing/locale/de/LC_MESSAGES/django.mo
juntagrico_billing/locale/de/LC_MESSAGES/django.po
juntagrico_billing/management/__init__.py
juntagrico_billing/management/commands/__init__.py
juntagrico_billing/management/commands/generate_billing_testdata.py
juntagrico_billing/migrations/0001_squashed_0012_post_1_4.py
juntagrico_billing/migrations/0002_bill_published.py
juntagrico_billing/migrations/0003_vat.py
juntagrico_billing/migrations/0004_settings_balancing_paymenttype.py
juntagrico_billing/migrations/0005_alter_settings_balancing_paymenttype_and_more.py
juntagrico_billing/migrations/__init__.py
juntagrico_billing/models/__init__.py
juntagrico_billing/models/account.py
juntagrico_billing/models/bill.py
juntagrico_billing/models/payment.py
juntagrico_billing/models/settings.py
juntagrico_billing/querysets/bill.py
juntagrico_billing/querysets/payment.py
juntagrico_billing/templates/admin/juntagrico_billing/bill/change_form.html
juntagrico_billing/templates/jb/accounting_summary.html
juntagrico_billing/templates/jb/bills_notify.html
juntagrico_billing/templates/jb/bookings_export.html
juntagrico_billing/templates/jb/memberbalance_export.html
juntagrico_billing/templates/jb/open_bills.html
juntagrico_billing/templates/jb/payments_upload.html
juntagrico_billing/templates/jb/pending_bills.html
juntagrico_billing/templates/jb/subscription_bookings.html
juntagrico_billing/templates/jb/unpublished_bills.html
juntagrico_billing-1.7.6.dist-info/licenses/LICENSE
juntagrico_billing-1.7.6.dist-info/METADATA
juntagrico_billing-1.7.6.dist-info/WHEEL
juntagrico_billing-1.7.6.dist-info/top_level.txt
juntagrico_billing-1.7.6.dist-info/RECORD
